MANIFEST.in
README.rst
pyramid_file_session.py
setup.cfg
setup.py
pyramid_file_session.egg-info/PKG-INFO
pyramid_file_session.egg-info/SOURCES.txt
pyramid_file_session.egg-info/dependency_links.txt
pyramid_file_session.egg-info/not-zip-safe
pyramid_file_session.egg-info/requires.txt
pyramid_file_session.egg-info/top_level.txt