Metadata-Version: 1.1
Name: pyramid-file-session
Version: 0.1.1
Summary: File-based session factory for Pyramid framework
Home-page: https://github.com/tark-hidden/pyramid_file_session
Author: Tark
Author-email: tark.hidden@gmail.com
License: BSD
Keywords: pyramid file session factory
Platform: any
Classifier: Environment :: Web Environment
Classifier: Intended Audience :: Developers
Classifier: License :: OSI Approved :: BSD License
Classifier: Operating System :: OS Independent
Classifier: Programming Language :: Python
Classifier: Programming Language :: Python :: 2
Classifier: Programming Language :: Python :: 2.6
Classifier: Programming Language :: Python :: 2.7
Classifier: Programming Language :: Python :: 3
Classifier: Programming Language :: Python :: 3.3
Classifier: Programming Language :: Python :: 3.4
Classifier: Topic :: Internet :: WWW/HTTP :: Dynamic Content
Classifier: Topic :: Software Development :: Libraries :: Python Modules
